{"operationConfig":{"name":"deleteTaskAttachment5481","type":"MappedToBackend","cachable":false,"smsEnabled":false,"security":"authorized_app_user","responseEncoding":"UTF-8","httpMethod":"GET","decodeResponseBody":false,"referencingEndpoint":"default","inputs":[{"id":"BINARY_GUID","scope":"request","dataType":"string","encode":true,"passNull":false},{"id":"GUID","scope":"request","dataType":"string","encode":true,"passNull":false},{"id":"SEQUENCE","scope":"request","dataType":"string","encode":true,"passNull":false}],"headers":[{"id":"KonySAP-Session-Key","scope":"request"}],"iMapping":"<?xml version=\"1.0\" encoding=\"UTF-8\" standalone=\"yes\"?><mapper xmlns=\"http://www.kony.com/ns/mapper\">  <map inputpath=\"request_in\" outputpath=\"request_out\">    <exec-function name=\"kony.gen.obj.TaskAttachment__hierarchy.toLOBFields\"/>  </map></mapper>","oMapping":"<?xml version=\"1.0\" encoding=\"UTF-8\" standalone=\"yes\"?><mapper xmlns=\"http://www.kony.com/ns/mapper\">  <map inputpath=\"response_in\" outputpath=\"response_out\">    <map inputpath=\"CFS_CONFIRMATION_ATTACH\" outputpath=\"TaskAttachment\">      <exec-function name=\"kony.gen.obj.TaskAttachment__hierarchy.fromLOBFields\"/>    </map>  </map></mapper>","applyCommonMapping":true,"entityMetadata":"{\"skyEntityMetadataRuntime\":{\"service\":\"CFS_TRANSACTIONS\",\"entityName\":\"CFS_CONFIRMATION_ATTACH\",\"fMap\":{\"GUID\":\"CFS_TRANSACTION_LINKS.LINK_DOC_GUID\"},\"sQuery\":\"CFS_DISTRIBUTION.DIST_KEY,CFS_TRANSACTION_HEADER.GUID,CFS_TRANSACTION_LINKS.GUID,CFS_TRANSACTION_CONF.GUID\",\"config\":{\"GUID\":\"true\",\"OPMODE\":\"true\"}}}","opcode":"delete","backendMeta":{"dataObjectName":"CFS_TRANSACTIONS","libraryName":"_SKYTECH_CFS","businessObjectName":"CFS_CONFIRMATION_ATTACH"},"relationshipHierarchyMapping":{"children":[{"children":[],"name":"media","selected":false}],"name":"TaskAttachment","selected":true}}}