{
    "@class": "com.kony.gen.viz.model.component.KVizButton",
    "DNDConfig": null,
    "__parentReadjusting__": false,
    "_height_": {
        "type": "string",
        "value": "50dp"
    },
    "_margin_": [
        6,
        6,
        6,
        6
    ],
    "_padding_": [
        0,
        0,
        0,
        0
    ],
    "_right_": {
        "type": "string",
        "value": "2%"
    },
    "_skin_": "s624ca78f3f74b6d9a5345292b6f78c7",
    "_text_": "",
    "_top_": {
        "type": "string",
        "value": "22%"
    },
    "_width_": {
        "type": "string",
        "value": "50dp"
    },
    "canUpdateUI": true,
    "containerweight": 100,
    "contentalignment": 5,
    "disabledSkins": {
        "focusSkin": "s2652d265cb647c7b0bfefde51090504"
    },
    "displaytext": true,
    "id": "btnLocationKA",
    "ide_onClick": "AS_Button_8deefa5f3b9843ef9a31ce8e3ca4f864",
    "info": null,
    "isvisible": true,
    "kuid": "4dc4098832f84ec187d7027f61d7503b",
    "name": "kony.ui.Button",
    "parent": "flexStockLocationDetailsKA",
    "pf": "frmTaskExecutionTabKA",
    "wType": "Button",
    "zindex": 1
}