{
    "@class": "com.kony.gen.viz.model.component.KVizButton",
    "DNDConfig": null,
    "__parentReadjusting__": false,
    "_height_": {
        "type": "string",
        "value": "50%"
    },
    "_margin_": [
        6,
        6,
        6,
        6
    ],
    "_padding_": [
        0,
        0,
        0,
        0
    ],
    "_right_": {
        "type": "string",
        "value": "6%"
    },
    "_skin_": "s2ffa4b4fd3a41babf976b3a1afe5ffb",
    "_text_": "",
    "_top_": {
        "type": "string",
        "value": "40.34%"
    },
    "_width_": {
        "type": "string",
        "value": "30%"
    },
    "canUpdateUI": true,
    "centery": {
        "type": "string",
        "value": "50%"
    },
    "containerweight": 100,
    "contentalignment": 5,
    "displaytext": true,
    "focusskin": "s107c7921b4a4a0a93dd270f93acf0ac",
    "id": "btnStartMaintenanceKA",
    "info": null,
    "isvisible": true,
    "kuid": "cffe16cab6514270b30a0bb34b38738e",
    "name": "kony.ui.Button",
    "parent": "flexPerformAppKA",
    "pf": "frmTaskExecutionTabKA",
    "texti18n": "i18n.common.statusMechine.startKA",
    "wType": "Button",
    "zindex": 1
}