{"type":"lob","custom":false,"junction":false,"customizable":false,"verbs":{"get":"getMapping"},"entityProperties":{"designTimeBackendMeta":{"libraryName":"_SKYTECH_EAM","dataObjectName":"EAM_DOB_MATERIAL","businessObjectName":"EAM_MAT_ATTACHMENT"},"UpdateTimeStampField":{"DateFormat":"yyyyMMddHHmmss","Name":"synctimestamp"},"backendMeta":{"libraryName":"_SKYTECH_EAM","dataObjectName":"EAM_DOB_MATERIAL","children":"[]","businessObjectName":"EAM_MAT_ATTACHMENT"},"SoftDeleteFlagField":{"ActiveValue":null,"InactiveValue":"X","Name":"SoftDeleteFlag"}},"commonMappings":[{"sourceFieldName":"AttachmentType_Id","targetField":"FILE_TYPE","type":"request_response"},{"sourceFieldName":"Material_Id","targetField":"MATERIAL_NUM","type":"request_response"},{"sourceFieldName":"Media_Id","targetField":"BINARY_NAME","type":"request_response"},{"sourceFieldName":"SoftDeleteFlag","targetField":"DELETE_IND","type":"request_response"},{"sourceFieldName":"synctimestamp","targetField":"TIMESTAMP","type":"request_response"}]}