[{"name":"createdby","sourceFieldname":"CREATED_BY","description":"CFS: Name of Person who Created the Object","dataType":"string","hasIndex":false,"unique":false,"primarykey":false,"namefield":false,"nullable":true,"custom":false,"createable":true,"updateable":true,"audit":false,"customizable":false,"fieldLength":12,"fieldProperties":{"autoGenerated":"false"}},{"name":"createdts","sourceFieldname":"CREATED_TSTAMP","description":"CFS: Created Timestamp","dataType":"string","hasIndex":false,"unique":false,"primarykey":false,"namefield":false,"nullable":true,"custom":false,"createable":true,"updateable":true,"audit":false,"customizable":false,"fieldLength":14,"fieldProperties":{"autoGenerated":"false"}},{"name":"FieldValue","sourceFieldname":"FIELD_VALUE","description":"CFS: Variable long text","dataType":"string","hasIndex":false,"unique":false,"primarykey":false,"namefield":false,"nullable":true,"custom":false,"createable":true,"updateable":true,"audit":false,"customizable":false,"fieldLength":2000,"fieldProperties":{"autoGenerated":"false"}},{"name":"id","sourceFieldname":"SURVEY_FVAL_ID","description":"CFS: Value","dataType":"string","hasIndex":false,"unique":false,"primarykey":true,"namefield":false,"nullable":false,"custom":false,"createable":true,"updateable":true,"audit":false,"customizable":false,"fieldLength":50,"fieldProperties":{"autoGenerated":"true"}},{"name":"lastmodifiedts","sourceFieldname":"MODIFIED_TSTAMP","description":"CFS: Created Timestamp","dataType":"string","hasIndex":false,"unique":false,"primarykey":false,"namefield":false,"nullable":true,"custom":false,"createable":true,"updateable":true,"audit":false,"customizable":false,"fieldLength":14,"fieldProperties":{"autoGenerated":"false"}},{"name":"modifiedby","sourceFieldname":"MODIFIED_BY","description":"CFS:Modified By","dataType":"string","hasIndex":false,"unique":false,"primarykey":false,"namefield":false,"nullable":true,"custom":false,"createable":true,"updateable":true,"audit":false,"customizable":false,"fieldLength":12,"fieldProperties":{"autoGenerated":"false"}},{"name":"SoftDeleteFlag","sourceFieldname":"DELETE_IND","description":"Delete local function data","dataType":"string","hasIndex":false,"unique":false,"primarykey":false,"namefield":false,"nullable":true,"custom":false,"createable":true,"updateable":true,"audit":false,"customizable":false,"fieldLength":1,"fieldProperties":{"autoGenerated":"false"}},{"name":"SurveyDefinition_id","sourceFieldname":"SURVEY_DEF_ID","description":"CFS: Survey Definition ID","dataType":"string","hasIndex":false,"unique":false,"primarykey":false,"namefield":false,"nullable":true,"custom":false,"createable":true,"updateable":true,"audit":false,"customizable":false,"fieldLength":50,"fieldProperties":{"autoGenerated":"false"}},{"name":"SurveyFieldDefintion_id","sourceFieldname":"SURVEY_FIELD_ID","description":"CFS: Field Definition ID","dataType":"string","hasIndex":false,"unique":false,"primarykey":false,"namefield":false,"nullable":true,"custom":false,"createable":true,"updateable":true,"audit":false,"customizable":false,"fieldLength":50,"fieldProperties":{"autoGenerated":"false"}},{"name":"SurveyResponse_id","sourceFieldname":"SRESPONSE_ID","description":"CFS: Survey Response ID","dataType":"string","hasIndex":false,"unique":false,"primarykey":false,"namefield":false,"nullable":true,"custom":false,"createable":true,"updateable":true,"audit":false,"customizable":false,"fieldLength":50,"fieldProperties":{"autoGenerated":"false"}},{"name":"SurveySection_id","sourceFieldname":"SURVEY_SEC_ID","description":"CFS: Survey Section ID","dataType":"string","hasIndex":false,"unique":false,"primarykey":false,"namefield":false,"nullable":true,"custom":false,"createable":true,"updateable":true,"audit":false,"customizable":false,"fieldLength":50,"fieldProperties":{"autoGenerated":"false"}},{"name":"TIMESTAMP","sourceFieldname":"TIMESTAMP","description":"Timestamp","dataType":"string","hasIndex":false,"unique":false,"primarykey":false,"namefield":false,"nullable":true,"custom":false,"createable":true,"updateable":true,"audit":false,"customizable":false,"fieldLength":14,"fieldProperties":{"autoGenerated":"false"}},{"name":"Unit_id","sourceFieldname":"UNIT_ID","description":"Unit of Measurement","dataType":"string","hasIndex":false,"unique":false,"primarykey":false,"namefield":false,"nullable":true,"custom":false,"createable":true,"updateable":true,"audit":false,"customizable":false,"fieldLength":3,"fieldProperties":{"autoGenerated":"false"}}]