{
    "DNDConfig": null,
    "__parentReadjusting__": false,
    "_height_": {
        "type": "ref",
        "value": "preferred"
    },
    "_left_": {
        "type": "string",
        "value": "3%"
    },
    "_margin_": [
        1,
        1,
        1,
        1
    ],
    "_padding_": [
        0,
        0,
        0,
        0
    ],
    "_skin_": "s261eb8ac74e428698e4e146650bfbde",
    "_text_": "Status",
    "_top_": {
        "type": "string",
        "value": "20%"
    },
    "_width_": {
        "type": "ref",
        "value": "preferred"
    },
    "_wrapping_": 2,
    "android": {
        "@class": "com.kony.gen.viz.model.component.property.label.AndroidLabelProperty",
        "psp": {
            "textCopyable": false
        },
        "render": true
    },
    "canUpdateUI": true,
    "containerweight": 100,
    "contentalignment": 4,
    "enabled": false,
    "hexpand": true,
    "id": "lblWorkStatusSummaryKA",
    "info": null,
    "ipad": {
        "psp": {
            "pasteboardType": 2,
            "textCopyable": false,
            "wrapping": 2
        },
        "render": true
    },
    "isvisible": true,
    "kuid": "cfafc98a59584bb6815d8e441aa2d041",
    "margininpixel": false,
    "name": "kony.ui.Label",
    "paddinginpixel": false,
    "parent": "flexWorkStatusSummaryKA",
    "pf": "frmCompleteOrderTabKA",
    "spa": {
        "@class": "com.kony.gen.viz.model.component.property.label.SPALabelProperty",
        "psp": {
            "textCopyable": false
        }
    },
    "spaandroidtablet": {
        "render": true
    },
    "spaipad": {
        "render": true
    },
    "spawindowstablet": {
        "render": true
    },
    "texti18n": "i18n.order.frmOrdersViewsKA.Status.ValueKA",
    "tooltip": "",
    "vexpand": false,
    "wType": "Label",
    "widgetalignment": 5,
    "windows8": {
        "render": true
    },
    "zindex": 1
}