{
    "p2kwiet1234563580554_btnHoldKA_onClick_seq0": {
        "id": "p2kwiet1234563580554_btnHoldKA_onClick_seq0",
        "type": "ACTION_SEQUENCE",
        "name": "frmTaskExecutionBtnHoldOnClickKA",
        "params": [{
            "name": "eventobject",
            "value": "eventobject"
        }],
        "language": "js",
        "actions": [{
            "id": "expression_onClick_7656112345635801930",
            "type": "ADD_SNIPPET",
            "codeSnippet": "var INSTANCE = kony.sdk.mvvm.KonyApplicationContext.getAppInstance();\n var controller = INSTANCE.getFormController(kony.application.getCurrentForm().id);\n controller.performAction(\"changeStatusForTask\");\n "
        }]
    }
}