{"operationConfig":{"name":"deleteMeasurePoint2267","type":"MappedToBackend","cachable":false,"smsEnabled":false,"security":"authorized_app_user","responseEncoding":"UTF-8","httpMethod":"GET","decodeResponseBody":false,"referencingEndpoint":"default","inputs":[{"id":"MEASURING_POINT","scope":"request","dataType":"string","encode":true,"passNull":false}],"headers":[{"id":"KonySAP-Session-Key","scope":"request"}],"applyCommonMapping":true,"entityMetadata":"{\"skyEntityMetadataRuntime\":{\"service\":\"EAM_DOB_ASSET\",\"entityName\":\"EAM_ASSET_MPOINT\",\"fMap\":{\"ASSET\":\"EAM_ASSET_HIER.ASSET\"},\"sQuery\":\"EAM_ASSET_HIER.ASSET,EAM_ASSET.ASSET\",\"config\":{\"OPMODE\":\"true\"}}}","opcode":"delete","backendMeta":{"dataObjectName":"EAM_DOB_ASSET","libraryName":"_SKYTECH_EAM","businessObjectName":"EAM_ASSET_MPOINT"},"relationshipHierarchyMapping":{"children":[{"children":[],"name":"MeasureValueHistory","selected":false}],"name":"MeasurePoint","selected":true}}}