{
    "DNDConfig": null,
    "__parentReadjusting__": false,
    "_height_": {
        "type": "string",
        "value": "100%"
    },
    "_left_": {
        "type": "string",
        "value": "22%"
    },
    "_margin_": [
        0,
        0,
        0,
        0
    ],
    "_orientation_": 6,
    "_padding_": [
        0,
        0,
        0,
        0
    ],
    "_percent_": true,
    "_skin_": "sc96884caf1449d88be2589964f162ba",
    "_top_": {
        "type": "string",
        "value": "0dp"
    },
    "_width_": {
        "type": "string",
        "value": "64.40%"
    },
    "allboxes": [],
    "autogrowmode": 0,
    "canUpdateUI": true,
    "children": [
        "lblInvoiceIDKA",
        "flxDateTimeKA",
        "lblIItemsKA"
    ],
    "clipbounds": true,
    "containerweight": 100,
    "enablescrolling": true,
    "id": "flxnvoiceDetailsKA",
    "info": null,
    "isvisible": true,
    "kuid": "e666e26b4a5c4ebd8a8a49663e51439f",
    "layouttype": 4,
    "name": "kony.ui.FlexContainer",
    "parent": "flxInvoiceKA",
    "pf": "frmInvoicePdfKA",
    "snapgridsize": 10,
    "snaptogrid": true,
    "wType": "FlexContainer",
    "widgetalignment": 1,
    "zindex": 1
}