{
    "@class": "com.kony.gen.viz.model.component.KVizImage2",
    "DNDConfig": null,
    "__parentReadjusting__": false,
    "_base64_": null,
    "_height_": {
        "type": "string",
        "value": "125px"
    },
    "_margin_": [
        0,
        0,
        0,
        0
    ],
    "_padding_": [
        0,
        0,
        0,
        0
    ],
    "_skin_": "se8e39958530489f8cb85a5c59fc3bf2",
    "_src_": "globalicon.png",
    "_top_": {
        "type": "string",
        "value": "1dp"
    },
    "_width_": {
        "type": "string",
        "value": "125px"
    },
    "canUpdateUI": true,
    "centerx": {
        "type": "string",
        "value": "50%"
    },
    "containerweight": 100,
    "context": {
        "channel": "mobile",
        "formID": "frmTaskResourcesListKA",
        "platform": "iphone",
        "templateType": "forms",
        "topLevelBox": null
    },
    "id": "imgGlobalSearch",
    "ide_onTouchStart": "AS_Image_0c7864ac51fd4500b7de72b6b57dff0e",
    "imagescalemode": 1,
    "info": null,
    "invokedProperty": "src",
    "isvisible": true,
    "kuid": "8e15a319967c4ceb9213d32cf6742170",
    "name": "kony.ui.Image2",
    "parent": "flxEmptyListKA",
    "pf": "frmTaskResourcesListKA",
    "srcType": 1,
    "wType": "Image",
    "widgetalignment": 5,
    "zindex": 1
}