{
    "AS_Button_e96efcf8bd8d45219d807905e00b874c": {
        "id": "AS_Button_e96efcf8bd8d45219d807905e00b874c",
        "type": "ACTION_SEQUENCE",
        "name": "frmCompleteOrderBtnClearAllOnClickKA",
        "params": [{
            "datatype": "collection",
            "name": "eventobject"
        }],
        "contextObj": {
            "name": "frmCompleteOrderTabKA",
            "type": "forms",
            "platform": "",
            "KUID": "4aee37dbb9e44ebba8f84cbb2533e73e"
        },
        "language": "js",
        "actions": [{
            "id": "ADD_SNIPPET__f82789b391194f09aed3ec2c5b05cc78",
            "type": "ADD_SNIPPET",
            "codeSnippet": "kony.sdk.mvvm.KonyApplicationContext.init();\nvar INSTANCE = kony.sdk.mvvm.KonyApplicationContext.getAppInstance();\nvar controller = INSTANCE.getFormController(kony.application.getCurrentForm().id);\ncontroller.performAction(\"onHidePopUpCall\");",
            "parentId": null,
            "callbackType": null
        }]
    }
}