{
    "AS_Switch_a948629aa3824c338dc27249bf940823": {
        "id": "AS_Switch_a948629aa3824c338dc27249bf940823",
        "type": "ACTION_SEQUENCE",
        "name": "frmCompleteOrderSwitchProblem8OnSlideKA",
        "params": [{
            "datatype": "collection",
            "name": "eventobject"
        }],
        "contextObj": {
            "name": "frmCompleteOrderTabKA",
            "type": "forms",
            "platform": "",
            "KUID": "4aee37dbb9e44ebba8f84cbb2533e73e"
        },
        "language": "js",
        "actions": [{
            "id": "ADD_SNIPPET__821240362df74b97b94905063739fc82",
            "type": "ADD_SNIPPET",
            "codeSnippet": "kony.sdk.mvvm.KonyApplicationContext.init();\nvar INSTANCE = kony.sdk.mvvm.KonyApplicationContext.getAppInstance();\nvar controller = INSTANCE.getFormController(kony.application.getCurrentForm().id);\ncontroller.performAction(\"switchToggleConfirmation\",[\"8\"]);\n\n",
            "parentId": null,
            "callbackType": null
        }]
    }
}