{
    "DNDConfig": null,
    "__parentReadjusting__": false,
    "_height_": {
        "type": "string",
        "value": "247dp"
    },
    "_left_": {
        "type": "string",
        "value": "315dp"
    },
    "_margin_": [
        0,
        0,
        0,
        0
    ],
    "_orientation_": 6,
    "_padding_": [
        0,
        0,
        0,
        0
    ],
    "_percent_": true,
    "_skin_": "sf98cf88ec834c30988a066324234c7d",
    "_top_": {
        "type": "string",
        "value": "53dp"
    },
    "_width_": {
        "type": "string",
        "value": "43.39%"
    },
    "allboxes": [],
    "autogrowmode": 0,
    "canUpdateUI": true,
    "children": [
        "CalendarExpenseKA"
    ],
    "clipbounds": true,
    "containerweight": 100,
    "enablescrolling": true,
    "id": "flexCalendarContainerKA",
    "info": null,
    "isvisible": false,
    "kuid": "5c6b08ec5a3c4cae80fe7e620d27ed6e",
    "layouttype": 2,
    "name": "kony.ui.FlexContainer",
    "parent": "flexEditExpensePopupContainerKA",
    "pf": "frmExpenseDetailsTabKA",
    "snapgridsize": 10,
    "snaptogrid": true,
    "wType": "FlexContainer",
    "widgetalignment": 1,
    "zindex": 3
}