{
    "DNDConfig": null,
    "__parentReadjusting__": false,
    "_data_": [
        {
            "lblCreatedByKA": {
                "@class": "com.viz.ide.model.segment.SimpleTextSegmentData",
                "i18nkey": "i18n.Notes.frmNotesDetailsKA.lblUpdatedCreatedByKA.ValueKA",
                "text": ""
            },
            "lblCreatedUpdatedOnKA": {
                "@class": "com.viz.ide.model.segment.SimpleTextSegmentData",
                "i18nkey": "i18n.Notes.frmNotesListKA.Created.ValueKA",
                "text": ""
            },
            "lblDurationKA": {
                "@class": "com.viz.ide.model.segment.SimpleTextSegmentData",
                "text": "5 Mins ago"
            },
            "lblLineKA": {
                "@class": "com.viz.ide.model.segment.SimpleTextSegmentData",
                "text": " "
            },
            "lblNotesDescKA": {
                "@class": "com.viz.ide.model.segment.SimpleTextSegmentData",
                "text": "Lorem ipsum dolor sit amet, consecotr lorefss adipiscumidg uislinmreynbifn…"
            },
            "lblTimeKA": {
                "@class": "com.viz.ide.model.segment.SimpleTextSegmentData",
                "text": "7:41 PM"
            }
        },
        {
            "lblCreatedByKA": {
                "@class": "com.viz.ide.model.segment.SimpleTextSegmentData",
                "i18nkey": "i18n.Notes.frmNotesDetailsKA.lblUpdatedCreatedByKA.ValueKA",
                "text": ""
            },
            "lblCreatedUpdatedOnKA": {
                "@class": "com.viz.ide.model.segment.SimpleTextSegmentData",
                "i18nkey": "i18n.Notes.frmNotesListKA.Updated.ValueKA",
                "text": ""
            },
            "lblDurationKA": {
                "@class": "com.viz.ide.model.segment.SimpleTextSegmentData",
                "text": "5 Mins ago"
            },
            "lblLineKA": {
                "@class": "com.viz.ide.model.segment.SimpleTextSegmentData",
                "text": "  "
            },
            "lblNotesDescKA": {
                "@class": "com.viz.ide.model.segment.SimpleTextSegmentData",
                "text": "Lorem ipsum dolor sit amet, consecotr lorefss adipiscumidg uislinmreynbifn…"
            },
            "lblTimeKA": {
                "@class": "com.viz.ide.model.segment.SimpleTextSegmentData",
                "text": "7:41 PM"
            }
        },
        {
            "lblCreatedByKA": {
                "@class": "com.viz.ide.model.segment.SimpleTextSegmentData",
                "i18nkey": "i18n.Notes.frmNotesDetailsKA.lblUpdatedCreatedByKA.ValueKA",
                "text": ""
            },
            "lblCreatedUpdatedOnKA": {
                "@class": "com.viz.ide.model.segment.SimpleTextSegmentData",
                "i18nkey": "i18n.Notes.frmNotesDetailsKA.lblUpdatedCreatedOnKA.ValueKA",
                "text": ""
            },
            "lblDurationKA": {
                "@class": "com.viz.ide.model.segment.SimpleTextSegmentData",
                "text": "5 Mins ago"
            },
            "lblLineKA": {
                "@class": "com.viz.ide.model.segment.SimpleTextSegmentData",
                "text": " "
            },
            "lblNotesDescKA": {
                "@class": "com.viz.ide.model.segment.SimpleTextSegmentData",
                "text": "Lorem ipsum dolor sit amet, consecotr lorefss adipiscumidg uislinmreynbifn…"
            },
            "lblTimeKA": {
                "@class": "com.viz.ide.model.segment.SimpleTextSegmentData",
                "text": "7:41 PM"
            }
        },
        {
            "lblCreatedByKA": {
                "@class": "com.viz.ide.model.segment.SimpleTextSegmentData",
                "i18nkey": "i18n.Notes.frmNotesDetailsKA.lblUpdatedCreatedByKA.ValueKA",
                "text": ""
            },
            "lblCreatedUpdatedOnKA": {
                "@class": "com.viz.ide.model.segment.SimpleTextSegmentData",
                "i18nkey": "i18n.Notes.frmNotesListKA.Created.ValueKA",
                "text": ""
            },
            "lblDurationKA": {
                "@class": "com.viz.ide.model.segment.SimpleTextSegmentData",
                "text": "5 Mins ago"
            },
            "lblLineKA": {
                "@class": "com.viz.ide.model.segment.SimpleTextSegmentData",
                "text": " "
            },
            "lblNotesDescKA": {
                "@class": "com.viz.ide.model.segment.SimpleTextSegmentData",
                "text": "Lorem ipsum dolor sit amet, consecotr lorefss adipiscumidg uislinmreynbifn…"
            },
            "lblTimeKA": {
                "@class": "com.viz.ide.model.segment.SimpleTextSegmentData",
                "text": "7:41 PM"
            }
        },
        {
            "lblCreatedByKA": {
                "@class": "com.viz.ide.model.segment.SimpleTextSegmentData",
                "i18nkey": "i18n.Notes.frmNotesDetailsKA.lblCreatedByKA.ValueKA",
                "text": ""
            },
            "lblCreatedUpdatedOnKA": {
                "@class": "com.viz.ide.model.segment.SimpleTextSegmentData",
                "i18nkey": "i18n.Notes.frmNotesDetailsKA.lblCreatedOnKA.ValueKA",
                "text": ""
            },
            "lblDurationKA": {
                "@class": "com.viz.ide.model.segment.SimpleTextSegmentData",
                "text": ""
            },
            "lblLineKA": {
                "@class": "com.viz.ide.model.segment.SimpleTextSegmentData",
                "text": " "
            },
            "lblNotesDescKA": {
                "@class": "com.viz.ide.model.segment.SimpleTextSegmentData",
                "text": ""
            },
            "lblTimeKA": {
                "@class": "com.viz.ide.model.segment.SimpleTextSegmentData",
                "text": ""
            }
        },
        {
            "lblCreatedByKA": {
                "@class": "com.viz.ide.model.segment.SimpleTextSegmentData",
                "text": ""
            },
            "lblCreatedUpdatedOnKA": {
                "@class": "com.viz.ide.model.segment.SimpleTextSegmentData",
                "text": ""
            },
            "lblDurationKA": {
                "@class": "com.viz.ide.model.segment.SimpleTextSegmentData",
                "text": ""
            },
            "lblLineKA": {
                "@class": "com.viz.ide.model.segment.SimpleTextSegmentData",
                "text": ""
            },
            "lblNotesDescKA": {
                "@class": "com.viz.ide.model.segment.SimpleTextSegmentData",
                "text": ""
            },
            "lblTimeKA": {
                "@class": "com.viz.ide.model.segment.SimpleTextSegmentData",
                "text": ""
            }
        },
        {
            "lblCreatedByKA": {
                "@class": "com.viz.ide.model.segment.SimpleTextSegmentData",
                "text": ""
            },
            "lblCreatedUpdatedOnKA": {
                "@class": "com.viz.ide.model.segment.SimpleTextSegmentData",
                "text": ""
            },
            "lblDurationKA": {
                "@class": "com.viz.ide.model.segment.SimpleTextSegmentData",
                "text": ""
            },
            "lblLineKA": {
                "@class": "com.viz.ide.model.segment.SimpleTextSegmentData",
                "text": ""
            },
            "lblNotesDescKA": {
                "@class": "com.viz.ide.model.segment.SimpleTextSegmentData",
                "text": ""
            },
            "lblTimeKA": {
                "@class": "com.viz.ide.model.segment.SimpleTextSegmentData",
                "text": ""
            }
        },
        {
            "lblCreatedByKA": {
                "@class": "com.viz.ide.model.segment.SimpleTextSegmentData",
                "text": ""
            },
            "lblCreatedUpdatedOnKA": {
                "@class": "com.viz.ide.model.segment.SimpleTextSegmentData",
                "text": ""
            },
            "lblDurationKA": {
                "@class": "com.viz.ide.model.segment.SimpleTextSegmentData",
                "text": ""
            },
            "lblLineKA": {
                "@class": "com.viz.ide.model.segment.SimpleTextSegmentData",
                "text": ""
            },
            "lblNotesDescKA": {
                "@class": "com.viz.ide.model.segment.SimpleTextSegmentData",
                "text": ""
            },
            "lblTimeKA": {
                "@class": "com.viz.ide.model.segment.SimpleTextSegmentData",
                "text": ""
            }
        },
        {
            "lblCreatedByKA": {
                "@class": "com.viz.ide.model.segment.SimpleTextSegmentData",
                "text": ""
            },
            "lblCreatedUpdatedOnKA": {
                "@class": "com.viz.ide.model.segment.SimpleTextSegmentData",
                "text": ""
            },
            "lblDurationKA": {
                "@class": "com.viz.ide.model.segment.SimpleTextSegmentData",
                "text": ""
            },
            "lblLineKA": {
                "@class": "com.viz.ide.model.segment.SimpleTextSegmentData",
                "text": ""
            },
            "lblNotesDescKA": {
                "@class": "com.viz.ide.model.segment.SimpleTextSegmentData",
                "text": ""
            },
            "lblTimeKA": {
                "@class": "com.viz.ide.model.segment.SimpleTextSegmentData",
                "text": ""
            }
        },
        {
            "lblCreatedByKA": {
                "@class": "com.viz.ide.model.segment.SimpleTextSegmentData",
                "text": ""
            },
            "lblCreatedUpdatedOnKA": {
                "@class": "com.viz.ide.model.segment.SimpleTextSegmentData",
                "text": ""
            },
            "lblDurationKA": {
                "@class": "com.viz.ide.model.segment.SimpleTextSegmentData",
                "text": ""
            },
            "lblLineKA": {
                "@class": "com.viz.ide.model.segment.SimpleTextSegmentData",
                "text": ""
            },
            "lblNotesDescKA": {
                "@class": "com.viz.ide.model.segment.SimpleTextSegmentData",
                "text": ""
            },
            "lblTimeKA": {
                "@class": "com.viz.ide.model.segment.SimpleTextSegmentData",
                "text": ""
            }
        },
        {
            "lblCreatedByKA": {
                "@class": "com.viz.ide.model.segment.SimpleTextSegmentData",
                "text": ""
            },
            "lblCreatedUpdatedOnKA": {
                "@class": "com.viz.ide.model.segment.SimpleTextSegmentData",
                "text": ""
            },
            "lblDurationKA": {
                "@class": "com.viz.ide.model.segment.SimpleTextSegmentData",
                "text": ""
            },
            "lblLineKA": {
                "@class": "com.viz.ide.model.segment.SimpleTextSegmentData",
                "text": ""
            },
            "lblNotesDescKA": {
                "@class": "com.viz.ide.model.segment.SimpleTextSegmentData",
                "text": ""
            },
            "lblTimeKA": {
                "@class": "com.viz.ide.model.segment.SimpleTextSegmentData",
                "text": ""
            }
        },
        {
            "lblCreatedByKA": {
                "@class": "com.viz.ide.model.segment.SimpleTextSegmentData",
                "text": ""
            },
            "lblCreatedUpdatedOnKA": {
                "@class": "com.viz.ide.model.segment.SimpleTextSegmentData",
                "text": ""
            },
            "lblDurationKA": {
                "@class": "com.viz.ide.model.segment.SimpleTextSegmentData",
                "text": ""
            },
            "lblLineKA": {
                "@class": "com.viz.ide.model.segment.SimpleTextSegmentData",
                "text": ""
            },
            "lblNotesDescKA": {
                "@class": "com.viz.ide.model.segment.SimpleTextSegmentData",
                "text": ""
            },
            "lblTimeKA": {
                "@class": "com.viz.ide.model.segment.SimpleTextSegmentData",
                "text": ""
            }
        },
        {
            "lblCreatedByKA": {
                "@class": "com.viz.ide.model.segment.SimpleTextSegmentData",
                "text": ""
            },
            "lblCreatedUpdatedOnKA": {
                "@class": "com.viz.ide.model.segment.SimpleTextSegmentData",
                "text": ""
            },
            "lblDurationKA": {
                "@class": "com.viz.ide.model.segment.SimpleTextSegmentData",
                "text": ""
            },
            "lblLineKA": {
                "@class": "com.viz.ide.model.segment.SimpleTextSegmentData",
                "text": ""
            },
            "lblNotesDescKA": {
                "@class": "com.viz.ide.model.segment.SimpleTextSegmentData",
                "text": ""
            },
            "lblTimeKA": {
                "@class": "com.viz.ide.model.segment.SimpleTextSegmentData",
                "text": ""
            }
        },
        {
            "lblCreatedByKA": {
                "@class": "com.viz.ide.model.segment.SimpleTextSegmentData",
                "text": ""
            },
            "lblCreatedUpdatedOnKA": {
                "@class": "com.viz.ide.model.segment.SimpleTextSegmentData",
                "text": ""
            },
            "lblDurationKA": {
                "@class": "com.viz.ide.model.segment.SimpleTextSegmentData",
                "text": ""
            },
            "lblLineKA": {
                "@class": "com.viz.ide.model.segment.SimpleTextSegmentData",
                "text": ""
            },
            "lblNotesDescKA": {
                "@class": "com.viz.ide.model.segment.SimpleTextSegmentData",
                "text": ""
            },
            "lblTimeKA": {
                "@class": "com.viz.ide.model.segment.SimpleTextSegmentData",
                "text": ""
            }
        }
    ],
    "_enabled_": false,
    "_height_": {
        "type": "string",
        "value": "100%"
    },
    "_indicator_": "none",
    "_left_": {
        "type": "string",
        "value": "0dp"
    },
    "_margin_": [
        0,
        0,
        0,
        0
    ],
    "_orientation_": 2,
    "_padding_": [
        0,
        0,
        0,
        0
    ],
    "_skin_": "seg2Normal",
    "_top_": {
        "type": "string",
        "value": "0dp"
    },
    "_width_": {
        "type": "string",
        "value": "100%"
    },
    "android": {
        "@class": "com.kony.gen.viz.model.container.property.segment2.AndroidSegment2Property",
        "psp": {
            "dockSectionHeaders": true
        },
        "render": true,
        "viewConfig": {
            "coverflowConfig": {
                "isCircular": true,
                "projectionAngle": 60
            }
        },
        "viewType": "tableview"
    },
    "canUpdateUI": true,
    "containerheightreference": 1,
    "containerweight": 100,
    "context": {
        "channel": "mobile",
        "formID": "AdvancedWidgetsSegements",
        "templateType": "segments",
        "topLevelBox": false
    },
    "counter": "013",
    "focusedindex": null,
    "focuseditem": null,
    "groupcells": false,
    "hasSections": false,
    "id": "segNotesListKA",
    "ide_onRowClick": "AS_Segment_5d7a7da1426048b6a11042c3fa2697d1",
    "info": null,
    "iphone": {
        "@class": "com.kony.gen.viz.model.container.property.segment2.IPhoneSegment2Property",
        "psp": {
            "bounces": false,
            "editStyle": "none",
            "enableDictionary": false,
            "indicator": "none",
            "progressIndicatorColor": "white",
            "searchCriteria": 1,
            "showProgressIndicator": false
        },
        "render": true,
        "viewConfig": {
            "coverflowConfig": {}
        },
        "viewType": "tableview"
    },
    "isvisible": true,
    "kuid": "p2kwiet19962346794072",
    "layoutalignment": 3,
    "margininpixel": false,
    "name": "kony.ui.SegmentedUI2",
    "needpageindicator": true,
    "paddinginpixel": false,
    "pageoffdotimage": "pageoffdot.png",
    "pageondotimage": "pageondot.png",
    "paginationconfig": {
        "position": "bottom"
    },
    "parent": "flxSegKA",
    "pf": "frmNotesListKA",
    "retainselection": false,
    "rowTemplateId": "p2kwiet19962346794085",
    "rowcounter": 13,
    "rowfocusskin": "s49df93815194fd78f6864c1b36c1913",
    "rowskin": "s68ecdbb8ea744e2807c4499986c822a",
    "rowtemplate": "flxNotesTmpKA",
    "screenlevelwidget": false,
    "scrollingevents": false,
    "seccounter": 0,
    "sectionheaderskin": "s4dbc03f1e84426abc6117d0cebfc2ab",
    "selectedRows": null,
    "selectedState": false,
    "selectedindex": null,
    "selectedindices": null,
    "selecteditems": null,
    "selectedsectionindex": 0,
    "selectionbehavior": "default",
    "selectionbehaviorconfig": {},
    "separatorcolor": "64646464",
    "separatorrequired": true,
    "separatorthickness": 0,
    "showscrollbars": false,
    "spa": {
        "@class": "com.kony.gen.viz.model.container.property.segment2.SPASegment2Property"
    },
    "spaan": {
        "@class": "com.kony.gen.viz.model.container.property.segment2.SPAAndroidSegment2Property",
        "render": true
    },
    "spabb": {
        "@class": "com.kony.gen.viz.model.container.property.segment2.SPABBSegment2Property",
        "render": false
    },
    "spaip": {
        "@class": "com.kony.gen.viz.model.container.property.segment2.SPAIPhoneSegment2Property",
        "render": true
    },
    "spawinphone8": {
        "@class": "com.kony.gen.viz.model.container.property.segment2.SPAWinPhone8Segment2Property",
        "render": true
    },
    "viewtype": "tableview",
    "wType": "Segment",
    "widgetalignment": 5,
    "widgetdatamap": {
        "flxCreatedKA": "flxCreatedKA",
        "flxNotesTmpKA": "flxNotesTmpKA",
        "lblCreatedByKA": "lblCreatedByKA",
        "lblCreatedUpdatedOnKA": "lblCreatedUpdatedOnKA",
        "lblDurationKA": "lblDurationKA",
        "lblLineKA": "lblLineKA",
        "lblNotesDescKA": "lblNotesDescKA",
        "lblTimeKA": "lblTimeKA",
        "tmpNotesListKA": "tmpNotesListKA"
    },
    "winphone8": {
        "@class": "com.kony.gen.viz.model.container.property.segment2.WinPhone8Segment2Property",
        "render": true
    },
    "zindex": 1
}